lazyfoodie/__init__.py
lazyfoodie/example.py
lazyfoodie-0.0.1a1.dist-info/LICENSE
lazyfoodie-0.0.1a1.dist-info/METADATA
lazyfoodie-0.0.1a1.dist-info/WHEEL
lazyfoodie-0.0.1a1.dist-info/top_level.txt
lazyfoodie-0.0.1a1.dist-info/RECORD
